lyzr_agents/__init__.py
lyzr_agents/base.py
lyzr_agents/client.py
lyzr_agents/storm/__init__.py
lyzr_agents/storm/agent.py
lyzr_agents/storm/config.py
lyzr_agents/storm/events.py
lyzr_agents/storm/result.py
lyzr_agents/storm/visualizer.py
lyzr_agents-0.1.2.dist-info/METADATA
lyzr_agents-0.1.2.dist-info/WHEEL
lyzr_agents-0.1.2.dist-info/RECORD
