Metadata-Version: 2.4
Name: lyzr-agents
Version: 0.1.2
Summary: A collection of template utility agents by Lyzr
Project-URL: Homepage, https://github.com/lyzr-ai/lyzr-agents
Project-URL: Documentation, https://docs.lyzr.ai/agents
Project-URL: Repository, https://github.com/lyzr-ai/lyzr-agents
Author-email: Lyzr <support@lyzr.ai>
License: MIT
Keywords: agents,ai,llm,lyzr,rag,storm
Classifier: Development Status :: 3 - Alpha
Classifier: Intended Audience :: Developers
Classifier: License :: OSI Approved :: MIT License
Classifier: Programming Language :: Python :: 3
Classifier: Programming Language :: Python :: 3.9
Classifier: Programming Language :: Python :: 3.10
Classifier: Programming Language :: Python :: 3.11
Classifier: Programming Language :: Python :: 3.12
Classifier: Topic :: Scientific/Engineering :: Artificial Intelligence
Requires-Python: >=3.9
Requires-Dist: requests>=2.28.0
Provides-Extra: all
Requires-Dist: black>=23.0.0; extra == 'all'
Requires-Dist: pytest-asyncio>=0.21.0; extra == 'all'
Requires-Dist: pytest>=7.0.0; extra == 'all'
Requires-Dist: requests>=2.28.0; extra == 'all'
Requires-Dist: rich>=13.0.0; extra == 'all'
Requires-Dist: ruff>=0.1.0; extra == 'all'
Provides-Extra: dev
Requires-Dist: black>=23.0.0; extra == 'dev'
Requires-Dist: pytest-asyncio>=0.21.0; extra == 'dev'
Requires-Dist: pytest>=7.0.0; extra == 'dev'
Requires-Dist: ruff>=0.1.0; extra == 'dev'
Provides-Extra: storm
Requires-Dist: requests>=2.28.0; extra == 'storm'
Requires-Dist: rich>=13.0.0; extra == 'storm'
